sql_on_dfs/__init__.py
sql_on_dfs/core.py
sql_on_dfs/utils.py
sql_on_dfs-0.2.0.dist-info/WHEEL
sql_on_dfs-0.2.0.dist-info/METADATA
sql_on_dfs-0.2.0.dist-info/RECORD
